README.rst
setup.py
django_feedback_api/__init__.py
django_feedback_api/admin.py
django_feedback_api/apps.py
django_feedback_api/models.py
django_feedback_api/serializers.py
django_feedback_api/tests.py
django_feedback_api/urls.py
django_feedback_api/views.py
django_feedback_api.egg-info/PKG-INFO
django_feedback_api.egg-info/SOURCES.txt
django_feedback_api.egg-info/dependency_links.txt
django_feedback_api.egg-info/requires.txt
django_feedback_api.egg-info/top_level.txt
django_feedback_api/migrations/0001_initial.py
django_feedback_api/migrations/__init__.py
django_feedback_api/signals/__init__.py
django_feedback_api/signals/handlers.py