Metadata-Version: 1.1
Name: django-feedback-api
Version: 0.2.0
Summary: RestAPI
Home-page: https://github.com/k0st1an/django-feedback-api
Author: Konstantin Kruglov
Author-email: kruglovk@gmail.com
License: Apache License Version 2.0
Platform: UNKNOWN
Classifier: Development Status :: 3 - Alpha
Classifier: License :: OSI Approved :: Apache Software License
Classifier: Programming Language :: Python :: 3 :: Only
Classifier: Operating System :: POSIX :: Linux
Classifier: Framework :: Django
Classifier: Framework :: Django :: 1.10
